carefulmodels/__init__.py
carefulmodels/inference.py
carefulmodels/models.py
carefulmodels/models/w-banding-fp16.onnx
carefulmodels/models/w-h264yuv-fp16.onnx
carefulmodels/models/w-mpeg2-fp16.onnx
carefulmodels/models/w-noise-fp16.onnx
carefulmodels/models/w-noiseuv2-fp16.onnx
carefulmodels/models/w-noisey-fp16.onnx
carefulmodels/models/w-scale-fp16.onnx
carefulmodels/models/w-sharp-fp16.onnx
carefulmodels-1.dist-info/METADATA
carefulmodels-1.dist-info/WHEEL
carefulmodels-1.dist-info/top_level.txt
carefulmodels-1.dist-info/RECORD
