Metadata-Version: 2.1
Name: carefulmodels
Version: 1
Summary: careful models
Home-page: https://github.com/wwww-wwww/carefulmodels
Author: wwww-wwww
Author-email: wvvwvvvvwvvw@gmail.com
Maintainer: wwww-wwww
Maintainer-email: wvvwvvvvwvvw@gmail.com
Classifier: Programming Language :: Python :: 3
Classifier: Operating System :: OS Independent
Requires-Python: >=3.11
Requires-Dist: vapoursynth
